{
  "BASE_URL": {
    "value": "${{RAILWAY_PUBLIC_DOMAIN}}",
    "description": "Public URL Plausible instance. Auto-set Railway public domain."
  },
  "SECRET_KEY_BASE": {
    "value": "${{secret(64)}}",
    "description": "64-byte random string cookie signing secrets. Auto-generated."
  },
  "DISABLE_REGISTRATION": {
    "value": "false",
    "description": "Set true disable public registration after creating admin account."
  },
  "ENABLE_EMAIL_VERIFICATION": {
    "value": "false",
    "description": "Set true require email verification new users."
  }
}
